apputils/__init__.py
apputils/mapper.py
apputils/parser.py
apputils/validator.py
apputils_xai-0.1.0.dist-info/METADATA
apputils_xai-0.1.0.dist-info/WHEEL
apputils_xai-0.1.0.dist-info/top_level.txt
apputils_xai-0.1.0.dist-info/RECORD
