Metadata-Version: 2.4
Name: apputils-xai
Version: 0.1.0
Summary: A utility library for no-code app generation
Home-page: https://github.com/Sumedh1599/apputils-xai
Author: NoLink Team
Author-email: your.email@example.com
Classifier: Programming Language :: Python :: 3
Classifier: License :: OSI Approved :: MIT License
Classifier: Operating System :: OS Independent
Requires-Python: >=3.6
Dynamic: author
Dynamic: author-email
Dynamic: classifier
Dynamic: description
Dynamic: description-content-type
Dynamic: home-page
Dynamic: requires-python
Dynamic: summary
